nonebot_plugin_calc_game/__init__.py
nonebot_plugin_calc_game/config.py
nonebot_plugin_calc_game/gamedata.py
nonebot_plugin_calc_game/gameplay.py
nonebot_plugin_calc_game/gamerror.py
nonebot_plugin_calc_game/tools.py
nonebot_plugin_calc_game-1.0.1.dist-info/LICENSE
nonebot_plugin_calc_game-1.0.1.dist-info/METADATA
nonebot_plugin_calc_game-1.0.1.dist-info/WHEEL
nonebot_plugin_calc_game-1.0.1.dist-info/RECORD
