Metadata-Version: 2.3
Name: nonebot-plugin-calc-game
Version: 1.0.1
Summary: 这是利用机器人复刻 计算器：游戏 的一个插件。通过给出的操作方式由当前数字达到计算目标。
License: MIT
Author: Yurchiu
Requires-Python: >=3.8,<4.0
Classifier: License :: OSI Approved :: MIT License
Classifier: Programming Language :: Python :: 3
Classifier: Programming Language :: Python :: 3.8
Classifier: Programming Language :: Python :: 3.9
Classifier: Programming Language :: Python :: 3.10
Classifier: Programming Language :: Python :: 3.11
Classifier: Programming Language :: Python :: 3.12
Classifier: Programming Language :: Python :: 3.13
Requires-Dist: nonebot-plugin-txt2img (>=0.4.1)
Requires-Dist: nonebot2 (>=2.3.2)
Requires-Dist: nonebot_plugin_alconna (>=0.55.1)
Project-URL: Homepage, https://github.com/Yurchiu/nonebot-plugin-calc-game
Project-URL: Repository, https://github.com/Yurchiu/nonebot-plugin-calc-game
